{
  "formatVersion": 1,
  "nodes": [
    {
      "id": "0",
      "name": "Camera",
      "children": [],
      "components": [
        {
          "type": "Camera",
          "config": {
            "mode": "orthographic",
            "fov": 45,
            "orthographicScale": 20,
            "viewport": {
              "x": 0,
              "y": 0,
              "width": 1,
              "height": 1
            },
            "depth": 0,
            "nearClippingPlane": 0.1,
            "farClippingPlane": 1000,
            "formatVersion": 1
          },
          "id": "0"
        },
        {
          "type": "Behavior",
          "config": {
            "behaviorName": "ShopManager",
            "propertyValues": {}
          },
          "id": "2"
        }
      ],
      "position": {
        "x": 0,
        "y": 0,
        "z": 10
      },
      "orientation": {
        "x": 0,
        "y": 0,
        "z": 0,
        "w": 1
      },
      "scale": {
        "x": 1,
        "y": 1,
        "z": 1
      },
      "visible": true,
      "layer": 0,
      "prefab": null
    },
    {
      "id": "1",
      "name": "Background",
      "children": [
        {
          "id": "31",
          "name": "Keeper",
          "children": [],
          "components": [
            {
              "type": "SpriteRenderer",
              "config": {
                "spriteAssetId": "166",
                "animationId": null,
                "horizontalFlip": false,
                "verticalFlip": false,
                "castShadow": false,
                "receiveShadow": false,
                "color": "ffffff",
                "overrideOpacity": false,
                "opacity": null,
                "materialType": "basic",
                "shaderAssetId": null,
                "formatVersion": 1
              },
              "id": "0"
            }
          ],
          "position": {
            "x": -4.5,
            "y": 2.4,
            "z": 0.1
          },
          "orientation": {
            "x": 0,
            "y": 0,
            "z": 0,
            "w": 1
          },
          "scale": {
            "x": 1,
            "y": 1,
            "z": 1
          },
          "visible": true,
          "layer": 0,
          "prefab": null
        },
        {
          "id": "32",
          "name": "Table",
          "children": [],
          "components": [
            {
              "type": "SpriteRenderer",
              "config": {
                "spriteAssetId": "169",
                "animationId": null,
                "horizontalFlip": false,
                "verticalFlip": false,
                "castShadow": false,
                "receiveShadow": false,
                "color": "ffffff",
                "overrideOpacity": false,
                "opacity": null,
                "materialType": "basic",
                "shaderAssetId": null,
                "formatVersion": 1
              },
              "id": "0"
            }
          ],
          "position": {
            "x": 0,
            "y": -7,
            "z": 0.2
          },
          "orientation": {
            "x": 0,
            "y": 0,
            "z": 0,
            "w": 1
          },
          "scale": {
            "x": 1,
            "y": 1,
            "z": 1
          },
          "visible": true,
          "layer": 0,
          "prefab": null
        }
      ],
      "components": [
        {
          "type": "SpriteRenderer",
          "config": {
            "spriteAssetId": "167",
            "animationId": null,
            "horizontalFlip": false,
            "verticalFlip": false,
            "castShadow": false,
            "receiveShadow": false,
            "color": "ffffff",
            "overrideOpacity": false,
            "opacity": null,
            "materialType": "basic",
            "shaderAssetId": null,
            "formatVersion": 1
          },
          "id": "0"
        }
      ],
      "position": {
        "x": 0,
        "y": 0,
        "z": 0
      },
      "orientation": {
        "x": 0,
        "y": 0,
        "z": 0,
        "w": 1
      },
      "scale": {
        "x": 1,
        "y": 1,
        "z": 1
      },
      "visible": true,
      "layer": 0,
      "prefab": null
    },
    {
      "id": "24",
      "name": "Tag",
      "children": [
        {
          "id": "39",
          "name": "Name",
          "children": [],
          "components": [
            {
              "type": "TextRenderer",
              "config": {
                "fontAssetId": "18",
                "text": "Name",
                "alignment": "center",
                "size": null,
                "color": "666666",
                "verticalAlignment": "center",
                "formatVersion": 2,
                "overrideOpacity": false,
                "opacity": null
              },
              "id": "0"
            }
          ],
          "position": {
            "x": 0,
            "y": 4.5,
            "z": 0.10000002384185791
          },
          "orientation": {
            "x": 0,
            "y": 0,
            "z": 0,
            "w": 1
          },
          "scale": {
            "x": 1,
            "y": 1,
            "z": 1
          },
          "visible": true,
          "layer": 0,
          "prefab": null
        },
        {
          "id": "40",
          "name": "Description",
          "children": [],
          "components": [
            {
              "type": "TextRenderer",
              "config": {
                "fontAssetId": "15",
                "text": "Description",
                "alignment": "left",
                "size": 32,
                "color": "888888",
                "verticalAlignment": "top",
                "formatVersion": 2,
                "overrideOpacity": false,
                "opacity": null
              },
              "id": "0"
            }
          ],
          "position": {
            "x": -4,
            "y": 3.5,
            "z": 0.10000002384185791
          },
          "orientation": {
            "x": 0,
            "y": 0,
            "z": 0,
            "w": 1
          },
          "scale": {
            "x": 1,
            "y": 1,
            "z": 1
          },
          "visible": true,
          "layer": 0,
          "prefab": null
        },
        {
          "id": "41",
          "name": "Price",
          "children": [
            {
              "id": "42",
              "name": "Gold",
              "children": [],
              "components": [
                {
                  "type": "SpriteRenderer",
                  "config": {
                    "spriteAssetId": "184",
                    "animationId": null,
                    "horizontalFlip": false,
                    "verticalFlip": false,
                    "castShadow": false,
                    "receiveShadow": false,
                    "color": "ffffff",
                    "overrideOpacity": false,
                    "opacity": null,
                    "materialType": "basic",
                    "shaderAssetId": null,
                    "formatVersion": 1
                  },
                  "id": "0"
                }
              ],
              "position": {
                "x": 0.6,
                "y": 0,
                "z": 0
              },
              "orientation": {
                "x": 0,
                "y": 0,
                "z": 0,
                "w": 1
              },
              "scale": {
                "x": 1,
                "y": 1,
                "z": 1
              },
              "visible": true,
              "layer": 0,
              "prefab": null
            }
          ],
          "components": [
            {
              "type": "TextRenderer",
              "config": {
                "fontAssetId": "157",
                "text": "10000",
                "alignment": "right",
                "size": null,
                "color": "ffffff",
                "verticalAlignment": "center",
                "formatVersion": 2,
                "overrideOpacity": false,
                "opacity": null
              },
              "id": "0"
            }
          ],
          "position": {
            "x": 1,
            "y": -0.8,
            "z": 0.1
          },
          "orientation": {
            "x": 0,
            "y": 0,
            "z": 0,
            "w": 1
          },
          "scale": {
            "x": 1,
            "y": 1,
            "z": 1
          },
          "visible": true,
          "layer": 0,
          "prefab": null
        }
      ],
      "components": [
        {
          "type": "SpriteRenderer",
          "config": {
            "spriteAssetId": "88",
            "animationId": null,
            "horizontalFlip": false,
            "verticalFlip": false,
            "castShadow": false,
            "receiveShadow": false,
            "color": "ffffff",
            "overrideOpacity": false,
            "opacity": null,
            "materialType": "basic",
            "shaderAssetId": null,
            "formatVersion": 1
          },
          "id": "0"
        }
      ],
      "position": {
        "x": 10,
        "y": 4.5,
        "z": 0.9
      },
      "orientation": {
        "x": 0,
        "y": 0,
        "z": 0,
        "w": 1
      },
      "scale": {
        "x": 1,
        "y": 1,
        "z": 1
      },
      "visible": false,
      "layer": 0,
      "prefab": null
    },
    {
      "id": "26",
      "name": "Item Spot",
      "children": [
        {
          "id": "25",
          "name": "Item",
          "children": [],
          "components": [
            {
              "type": "SpriteRenderer",
              "config": {
                "spriteAssetId": "234",
                "animationId": null,
                "horizontalFlip": false,
                "verticalFlip": false,
                "castShadow": false,
                "receiveShadow": false,
                "color": "ffffff",
                "overrideOpacity": false,
                "opacity": null,
                "materialType": "basic",
                "shaderAssetId": null,
                "formatVersion": 1
              },
              "id": "0"
            },
            {
              "type": "Behavior",
              "config": {
                "behaviorName": "ItemSlideBehavior",
                "propertyValues": {}
              },
              "id": "1"
            }
          ],
          "position": {
            "x": 0,
            "y": 0,
            "z": 0
          },
          "orientation": {
            "x": 0,
            "y": 0,
            "z": 0,
            "w": 1
          },
          "scale": {
            "x": 2,
            "y": 2,
            "z": 1
          },
          "visible": false,
          "layer": 0,
          "prefab": null
        }
      ],
      "components": [],
      "position": {
        "x": -4,
        "y": -4,
        "z": 1
      },
      "orientation": {
        "x": 0,
        "y": 0,
        "z": 0,
        "w": 1
      },
      "scale": {
        "x": 0.75,
        "y": 0.75,
        "z": 0.75
      },
      "visible": true,
      "layer": 0,
      "prefab": null
    },
    {
      "id": "4",
      "name": "Sale Status",
      "children": [],
      "components": [
        {
          "type": "TextRenderer",
          "config": {
            "fontAssetId": "15",
            "text": "Sale ?/?",
            "alignment": "right",
            "size": null,
            "color": "cccccc",
            "verticalAlignment": "top",
            "formatVersion": 2,
            "overrideOpacity": false,
            "opacity": null
          },
          "id": "0"
        }
      ],
      "position": {
        "x": 5,
        "y": 9.8,
        "z": 1
      },
      "orientation": {
        "x": 0,
        "y": 0,
        "z": 0,
        "w": 1
      },
      "scale": {
        "x": 1,
        "y": 1,
        "z": 1
      },
      "visible": false,
      "layer": 0,
      "prefab": null
    },
    {
      "id": "3",
      "name": "Countdown",
      "children": [],
      "components": [
        {
          "type": "TextRenderer",
          "config": {
            "fontAssetId": "157",
            "text": "",
            "alignment": "right",
            "size": null,
            "color": "ffffff",
            "verticalAlignment": "center",
            "formatVersion": 2,
            "overrideOpacity": false,
            "opacity": null
          },
          "id": "1"
        }
      ],
      "position": {
        "x": 5,
        "y": 7.5,
        "z": 1
      },
      "orientation": {
        "x": 0,
        "y": 0,
        "z": 0,
        "w": 1
      },
      "scale": {
        "x": 1,
        "y": 1,
        "z": 1
      },
      "visible": true,
      "layer": 0,
      "prefab": null
    },
    {
      "id": "6",
      "name": "Welcome",
      "children": [
        {
          "id": "9",
          "name": "Title",
          "children": [],
          "components": [
            {
              "type": "TextRenderer",
              "config": {
                "fontAssetId": "18",
                "text": "Welcome!",
                "alignment": "right",
                "size": null,
                "color": null,
                "verticalAlignment": "top",
                "formatVersion": 2,
                "overrideOpacity": false,
                "opacity": null
              },
              "id": "0"
            }
          ],
          "position": {
            "x": 14,
            "y": 9,
            "z": 0
          },
          "orientation": {
            "x": 0,
            "y": 0,
            "z": 0,
            "w": 1
          },
          "scale": {
            "x": 1,
            "y": 1,
            "z": 1
          },
          "visible": true,
          "layer": 0,
          "prefab": null
        },
        {
          "id": "7",
          "name": "Flash sale",
          "children": [
            {
              "id": "8",
              "name": "Button",
              "children": [],
              "components": [
                {
                  "type": "SpriteRenderer",
                  "config": {
                    "spriteAssetId": "103",
                    "animationId": "0",
                    "horizontalFlip": false,
                    "verticalFlip": false,
                    "castShadow": false,
                    "receiveShadow": false,
                    "color": "ffffff",
                    "overrideOpacity": false,
                    "opacity": null,
                    "materialType": "basic",
                    "shaderAssetId": null,
                    "formatVersion": 1
                  },
                  "id": "0"
                }
              ],
              "position": {
                "x": -2.5,
                "y": -11,
                "z": 0
              },
              "orientation": {
                "x": 0,
                "y": 0,
                "z": 0,
                "w": 1
              },
              "scale": {
                "x": 1,
                "y": 1,
                "z": 1
              },
              "visible": true,
              "layer": 0,
              "prefab": null
            }
          ],
          "components": [
            {
              "type": "TextRenderer",
              "config": {
                "fontAssetId": "15",
                "text": "\n\nI only do FLASH\nsales. You'll have\nfive seconds to\ndecide whether\nto buy OR not.\n\nReady?\n\n- Press           -",
                "alignment": "right",
                "size": null,
                "color": null,
                "verticalAlignment": "top",
                "formatVersion": 2,
                "overrideOpacity": false,
                "opacity": null
              },
              "id": "0"
            }
          ],
          "position": {
            "x": 14,
            "y": 9,
            "z": 0
          },
          "orientation": {
            "x": 0,
            "y": 0,
            "z": 0,
            "w": 1
          },
          "scale": {
            "x": 1,
            "y": 1,
            "z": 1
          },
          "visible": true,
          "layer": 0,
          "prefab": null
        }
      ],
      "components": [],
      "position": {
        "x": 0,
        "y": 0,
        "z": 1
      },
      "orientation": {
        "x": 0,
        "y": 0,
        "z": 0,
        "w": 1
      },
      "scale": {
        "x": 1,
        "y": 1,
        "z": 1
      },
      "visible": true,
      "layer": 0,
      "prefab": null
    },
    {
      "id": "5",
      "name": "Sale",
      "children": [
        {
          "id": "16",
          "name": "P1",
          "children": [
            {
              "id": "14",
              "name": "Buy Button P1",
              "children": [],
              "components": [
                {
                  "type": "SpriteRenderer",
                  "config": {
                    "spriteAssetId": "103",
                    "animationId": "0",
                    "horizontalFlip": false,
                    "verticalFlip": false,
                    "castShadow": false,
                    "receiveShadow": false,
                    "color": "ffffff",
                    "overrideOpacity": false,
                    "opacity": null,
                    "materialType": "basic",
                    "shaderAssetId": null,
                    "formatVersion": 1
                  },
                  "id": "0"
                }
              ],
              "position": {
                "x": 1.5,
                "y": -1.5,
                "z": 0
              },
              "orientation": {
                "x": 0,
                "y": 0,
                "z": 0,
                "w": 1
              },
              "scale": {
                "x": 1,
                "y": 1,
                "z": 1
              },
              "visible": true,
              "layer": 0,
              "prefab": null
            },
            {
              "id": "28",
              "name": "Gold Amount",
              "children": [
                {
                  "id": "27",
                  "name": "Gold",
                  "children": [],
                  "components": [
                    {
                      "type": "SpriteRenderer",
                      "config": {
                        "spriteAssetId": "184",
                        "animationId": null,
                        "horizontalFlip": false,
                        "verticalFlip": false,
                        "castShadow": false,
                        "receiveShadow": false,
                        "color": "ffffff",
                        "overrideOpacity": false,
                        "opacity": null,
                        "materialType": "basic",
                        "shaderAssetId": null,
                        "formatVersion": 1
                      },
                      "id": "0"
                    }
                  ],
                  "position": {
                    "x": 0.75,
                    "y": 0,
                    "z": 0
                  },
                  "orientation": {
                    "x": 0,
                    "y": 0,
                    "z": 0,
                    "w": 1
                  },
                  "scale": {
                    "x": 1,
                    "y": 1,
                    "z": 1
                  },
                  "visible": true,
                  "layer": 0,
                  "prefab": null
                }
              ],
              "components": [
                {
                  "type": "TextRenderer",
                  "config": {
                    "fontAssetId": "157",
                    "text": "0",
                    "alignment": "right",
                    "size": null,
                    "color": null,
                    "verticalAlignment": "center",
                    "formatVersion": 2,
                    "overrideOpacity": false,
                    "opacity": null
                  },
                  "id": "0"
                }
              ],
              "position": {
                "x": 7.25,
                "y": -1.5,
                "z": 0
              },
              "orientation": {
                "x": 0,
                "y": 0,
                "z": 0,
                "w": 1
              },
              "scale": {
                "x": 1,
                "y": 1,
                "z": 1
              },
              "visible": true,
              "layer": 0,
              "prefab": null
            },
            {
              "id": "33",
              "name": "Health",
              "children": [
                {
                  "id": "34",
                  "name": "Bar",
                  "children": [],
                  "components": [
                    {
                      "type": "SpriteRenderer",
                      "config": {
                        "spriteAssetId": "44",
                        "animationId": null,
                        "horizontalFlip": false,
                        "verticalFlip": false,
                        "castShadow": false,
                        "receiveShadow": false,
                        "color": "ffffff",
                        "overrideOpacity": false,
                        "opacity": null,
                        "materialType": "basic",
                        "shaderAssetId": null,
                        "formatVersion": 1
                      },
                      "id": "0"
                    }
                  ],
                  "position": {
                    "x": 0,
                    "y": 0,
                    "z": 0.1
                  },
                  "orientation": {
                    "x": 0,
                    "y": 0,
                    "z": 0,
                    "w": 1
                  },
                  "scale": {
                    "x": 1,
                    "y": 1,
                    "z": 1
                  },
                  "visible": true,
                  "layer": 0,
                  "prefab": null
                },
                {
                  "id": "35",
                  "name": "Top",
                  "children": [],
                  "components": [
                    {
                      "type": "SpriteRenderer",
                      "config": {
                        "spriteAssetId": "45",
                        "animationId": null,
                        "horizontalFlip": false,
                        "verticalFlip": false,
                        "castShadow": false,
                        "receiveShadow": false,
                        "color": "ffffff",
                        "overrideOpacity": false,
                        "opacity": null,
                        "materialType": "basic",
                        "shaderAssetId": null,
                        "formatVersion": 1
                      },
                      "id": "0"
                    }
                  ],
                  "position": {
                    "x": 0,
                    "y": 0,
                    "z": 0.2
                  },
                  "orientation": {
                    "x": 0,
                    "y": 0,
                    "z": 0,
                    "w": 1
                  },
                  "scale": {
                    "x": 1,
                    "y": 1,
                    "z": 1
                  },
                  "visible": true,
                  "layer": 0,
                  "prefab": null
                }
              ],
              "components": [
                {
                  "type": "SpriteRenderer",
                  "config": {
                    "spriteAssetId": "43",
                    "animationId": null,
                    "horizontalFlip": false,
                    "verticalFlip": false,
                    "castShadow": false,
                    "receiveShadow": false,
                    "color": "ffffff",
                    "overrideOpacity": false,
                    "opacity": null,
                    "materialType": "basic",
                    "shaderAssetId": null,
                    "formatVersion": 1
                  },
                  "id": "0"
                }
              ],
              "position": {
                "x": 7,
                "y": 0,
                "z": 0
              },
              "orientation": {
                "x": 0,
                "y": 0,
                "z": 0,
                "w": 1
              },
              "scale": {
                "x": 1,
                "y": 1,
                "z": 1
              },
              "visible": true,
              "layer": 0,
              "prefab": null
            }
          ],
          "components": [
            {
              "type": "TextRenderer",
              "config": {
                "fontAssetId": "15",
                "text": "Player 1 ",
                "alignment": "left",
                "size": null,
                "color": null,
                "verticalAlignment": "center",
                "formatVersion": 2,
                "overrideOpacity": false,
                "opacity": null
              },
              "id": "0"
            }
          ],
          "position": {
            "x": 6,
            "y": 2,
            "z": 0
          },
          "orientation": {
            "x": 0,
            "y": 0,
            "z": 0,
            "w": 1
          },
          "scale": {
            "x": 1,
            "y": 1,
            "z": 1
          },
          "visible": true,
          "layer": 0,
          "prefab": null
        },
        {
          "id": "17",
          "name": "P2",
          "children": [
            {
              "id": "10",
              "name": "Buy Button P2",
              "children": [],
              "components": [
                {
                  "type": "SpriteRenderer",
                  "config": {
                    "spriteAssetId": "159",
                    "animationId": "0",
                    "horizontalFlip": false,
                    "verticalFlip": false,
                    "castShadow": false,
                    "receiveShadow": false,
                    "color": "ffffff",
                    "overrideOpacity": false,
                    "opacity": null,
                    "materialType": "basic",
                    "shaderAssetId": null,
                    "formatVersion": 1
                  },
                  "id": "0"
                }
              ],
              "position": {
                "x": 1.5,
                "y": -1.5,
                "z": 0
              },
              "orientation": {
                "x": 0,
                "y": 0,
                "z": 0,
                "w": 1
              },
              "scale": {
                "x": 1,
                "y": 1,
                "z": 1
              },
              "visible": true,
              "layer": 0,
              "prefab": null
            },
            {
              "id": "30",
              "name": "Gold Amount",
              "children": [
                {
                  "id": "29",
                  "name": "Gold",
                  "children": [],
                  "components": [
                    {
                      "type": "SpriteRenderer",
                      "config": {
                        "spriteAssetId": "184",
                        "animationId": null,
                        "horizontalFlip": false,
                        "verticalFlip": false,
                        "castShadow": false,
                        "receiveShadow": false,
                        "color": "ffffff",
                        "overrideOpacity": false,
                        "opacity": null,
                        "materialType": "basic",
                        "shaderAssetId": null,
                        "formatVersion": 1
                      },
                      "id": "0"
                    }
                  ],
                  "position": {
                    "x": 0.75,
                    "y": 0,
                    "z": 0
                  },
                  "orientation": {
                    "x": 0,
                    "y": 0,
                    "z": 0,
                    "w": 1
                  },
                  "scale": {
                    "x": 1,
                    "y": 1,
                    "z": 1
                  },
                  "visible": true,
                  "layer": 0,
                  "prefab": null
                }
              ],
              "components": [
                {
                  "type": "TextRenderer",
                  "config": {
                    "fontAssetId": "157",
                    "text": "0",
                    "alignment": "right",
                    "size": null,
                    "color": null,
                    "verticalAlignment": "center",
                    "formatVersion": 2,
                    "overrideOpacity": false,
                    "opacity": null
                  },
                  "id": "0"
                }
              ],
              "position": {
                "x": 7,
                "y": -1.5,
                "z": 0
              },
              "orientation": {
                "x": 0,
                "y": 0,
                "z": 0,
                "w": 1
              },
              "scale": {
                "x": 1,
                "y": 1,
                "z": 1
              },
              "visible": true,
              "layer": 0,
              "prefab": null
            },
            {
              "id": "36",
              "name": "Health",
              "children": [
                {
                  "id": "37",
                  "name": "Bar",
                  "children": [],
                  "components": [
                    {
                      "type": "SpriteRenderer",
                      "config": {
                        "spriteAssetId": "44",
                        "animationId": null,
                        "horizontalFlip": false,
                        "verticalFlip": false,
                        "castShadow": false,
                        "receiveShadow": false,
                        "color": "ffffff",
                        "overrideOpacity": false,
                        "opacity": null,
                        "materialType": "basic",
                        "shaderAssetId": null,
                        "formatVersion": 1
                      },
                      "id": "0"
                    }
                  ],
                  "position": {
                    "x": 0,
                    "y": 0,
                    "z": 0.1
                  },
                  "orientation": {
                    "x": 0,
                    "y": 0,
                    "z": 0,
                    "w": 1
                  },
                  "scale": {
                    "x": 1,
                    "y": 1,
                    "z": 1
                  },
                  "visible": true,
                  "layer": 0,
                  "prefab": null
                },
                {
                  "id": "38",
                  "name": "Top",
                  "children": [],
                  "components": [
                    {
                      "type": "SpriteRenderer",
                      "config": {
                        "spriteAssetId": "45",
                        "animationId": null,
                        "horizontalFlip": false,
                        "verticalFlip": false,
                        "castShadow": false,
                        "receiveShadow": false,
                        "color": "ffffff",
                        "overrideOpacity": false,
                        "opacity": null,
                        "materialType": "basic",
                        "shaderAssetId": null,
                        "formatVersion": 1
                      },
                      "id": "0"
                    }
                  ],
                  "position": {
                    "x": 0,
                    "y": 0,
                    "z": 0.2
                  },
                  "orientation": {
                    "x": 0,
                    "y": 0,
                    "z": 0,
                    "w": 1
                  },
                  "scale": {
                    "x": 1,
                    "y": 1,
                    "z": 1
                  },
                  "visible": true,
                  "layer": 0,
                  "prefab": null
                }
              ],
              "components": [
                {
                  "type": "SpriteRenderer",
                  "config": {
                    "spriteAssetId": "43",
                    "animationId": null,
                    "horizontalFlip": false,
                    "verticalFlip": false,
                    "castShadow": false,
                    "receiveShadow": false,
                    "color": "ffffff",
                    "overrideOpacity": false,
                    "opacity": null,
                    "materialType": "basic",
                    "shaderAssetId": null,
                    "formatVersion": 1
                  },
                  "id": "0"
                }
              ],
              "position": {
                "x": 7,
                "y": 0,
                "z": 0
              },
              "orientation": {
                "x": 0,
                "y": 0,
                "z": 0,
                "w": 1
              },
              "scale": {
                "x": 1,
                "y": 1,
                "z": 1
              },
              "visible": true,
              "layer": 0,
              "prefab": null
            }
          ],
          "components": [
            {
              "type": "TextRenderer",
              "config": {
                "fontAssetId": "15",
                "text": "Player 2",
                "alignment": "left",
                "size": null,
                "color": null,
                "verticalAlignment": "center",
                "formatVersion": 2,
                "overrideOpacity": false,
                "opacity": null
              },
              "id": "0"
            }
          ],
          "position": {
            "x": 6,
            "y": -1.25,
            "z": 0
          },
          "orientation": {
            "x": 0,
            "y": 0,
            "z": 0,
            "w": 1
          },
          "scale": {
            "x": 1,
            "y": 1,
            "z": 1
          },
          "visible": true,
          "layer": 0,
          "prefab": null
        }
      ],
      "components": [],
      "position": {
        "x": 0,
        "y": 0,
        "z": 1
      },
      "orientation": {
        "x": 0,
        "y": 0,
        "z": 0,
        "w": 1
      },
      "scale": {
        "x": 1,
        "y": 1,
        "z": 1
      },
      "visible": false,
      "layer": 0,
      "prefab": null
    }
  ]
}